LICENSE
MANIFEST.in
README.md
setup.cfg
setup.py
cookiecutter/__init__.py
cookiecutter/__main__.py
cookiecutter/cli.py
cookiecutter/config.py
cookiecutter/environment.py
cookiecutter/exceptions.py
cookiecutter/extensions.py
cookiecutter/find.py
cookiecutter/generate.py
cookiecutter/hooks.py
cookiecutter/log.py
cookiecutter/main.py
cookiecutter/prompt.py
cookiecutter/replay.py
cookiecutter/repository.py
cookiecutter/utils.py
cookiecutter/vcs.py
cookiecutter/zipfile.py
cookiecutter_cc.egg-info/PKG-INFO
cookiecutter_cc.egg-info/SOURCES.txt
cookiecutter_cc.egg-info/dependency_links.txt
cookiecutter_cc.egg-info/entry_points.txt
cookiecutter_cc.egg-info/not-zip-safe
cookiecutter_cc.egg-info/requires.txt
cookiecutter_cc.egg-info/top_level.txt
docs/Makefile
docs/conf.py
docs/cookiecutter.rst
docs/first_steps.rst
docs/index.rst
docs/installation.rst
docs/make.bat
docs/overview.rst
docs/sprint-contributors.rst
docs/troubleshooting.rst
docs/tutorial1.rst
docs/tutorial2.rst
docs/tutorials.rst
docs/usage.rst
docs/advanced/calling_from_python.rst
docs/advanced/choice_variables.rst
docs/advanced/cli_options.rst
docs/advanced/copy_without_render.rst
docs/advanced/dict_variables.rst
docs/advanced/hooks.rst
docs/advanced/index.rst
docs/advanced/injecting_context.rst
docs/advanced/replay.rst
docs/advanced/suppressing_prompts.rst
docs/advanced/template_extensions.rst
docs/advanced/templates_in_context.rst
docs/advanced/user_config.rst
tests/__init__.py
tests/conftest.py
tests/test_abort_generate_on_hook_error.py
tests/test_cli.py
tests/test_cookiecutter_invocation.py
tests/test_cookiecutter_local_no_input.py
tests/test_cookiecutter_local_with_input.py
tests/test_custom_extensions_in_hooks.py
tests/test_default_extensions.py
tests/test_environment.py
tests/test_exceptions.py
tests/test_find.py
tests/test_generate_context.py
tests/test_generate_copy_without_render.py
tests/test_generate_file.py
tests/test_generate_files.py
tests/test_generate_hooks.py
tests/test_get_config.py
tests/test_get_user_config.py
tests/test_hooks.py
tests/test_log.py
tests/test_main.py
tests/test_output_folder.py
tests/test_preferred_encoding.py
tests/test_prompt.py
tests/test_read_repo_password.py
tests/test_read_user_choice.py
tests/test_read_user_dict.py
