Metadata-Version: 2.1
Name: cookiecutter-cc
Version: 1.6.0
Summary: A command-line utility that creates projects from project templates, e.g. creating a Python package project from a Python package project template.
Home-page: https://github.com/cookiecutter/cookiecutter
Author: Bernardas Ališauskas
Author-email: bernardas.alisauskas@pm.me
License: BSD
Keywords: cookiecutter,Python,projects,project templates,Jinja2,skeleton,scaffolding,project directory,setup.py,package,packaging
Platform: UNKNOWN
Classifier: Development Status :: 5 - Production/Stable
Classifier: Environment :: Console
Classifier: Intended Audience :: Developers
Classifier: Natural Language :: English
Classifier: License :: OSI Approved :: BSD License
Classifier: Programming Language :: Python
Classifier: Programming Language :: Python :: 2
Classifier: Programming Language :: Python :: 2.7
Classifier: Programming Language :: Python :: 3
Classifier: Programming Language :: Python :: 3.5
Classifier: Programming Language :: Python :: 3.6
Classifier: Programming Language :: Python :: 3.7
Classifier: Programming Language :: Python :: Implementation :: CPython
Classifier: Programming Language :: Python :: Implementation :: PyPy
Classifier: Topic :: Software Development
Requires-Python: >=2.7, !=3.0.*, !=3.1.*, !=3.2.*, !=3.3.*, !=3.4.*
